correlation_logger/__init__.py
correlation_logger/cloudwatch_handler.py
correlation_logger/logger.py
correlation_logger-1.1.0.dist-info/LICENSE
correlation_logger-1.1.0.dist-info/METADATA
correlation_logger-1.1.0.dist-info/WHEEL
correlation_logger-1.1.0.dist-info/entry_points.txt
correlation_logger-1.1.0.dist-info/RECORD
