Metadata-Version: 2.1
Name: correlation-logger
Version: 1.1.0
Summary: Python logger for logging using correlation id in production.
Author: Dr. Nobel Khandaker
Author-email: nobel@outlook.com
Requires-Python: >=3.10,<4.0
Classifier: Programming Language :: Python :: 3
Classifier: Programming Language :: Python :: 3.10
Classifier: Programming Language :: Python :: 3.11
Classifier: Programming Language :: Python :: 3.12
Requires-Dist: boto3 (>=1.34.103,<2.0.0)
Requires-Dist: moto (>=5.0.10,<6.0.0)
Requires-Dist: pytest (>=8.2.2,<9.0.0)
Requires-Dist: uuid (>=1.30,<2.0)
